{
  "tool_id": "63e87bb1-1bf6-4004-8435-15855f8b5c78",
  "tool_name": "Hardware Quote Generator",
  "description": "生成电脑配置报价单",
  "code": "\ndef execute(params: dict, context: dict) -> dict:\n    \"\"\"生成电脑配置报价单\"\"\"\n    budget = params.get(\"budget\", 5000)\n    usage = params.get(\"usage\", \"办公\")\n    \n    configurations = {\n        \"办公\": {\n            \"CPU\": \"Intel i5-14400\",\n            \"主板\": \"B760M\",\n            \"内存\": \"16GB DDR4\",\n            \"硬盘\": \"512GB SSD\",\n            \"显卡\": \"核显\",\n            \"电源\": \"400W\",\n            \"总价\": f\"{budget}元\"\n        },\n        \"游戏\": {\n            \"CPU\": \"Intel i7-14700K\",\n            \"主板\": \"Z790\",\n            \"内存\": \"32GB DDR5\",\n            \"硬盘\": \"1TB SSD\",\n            \"显卡\": \"RTX 4070\",\n            \"电源\": \"750W\",\n            \"总价\": f\"{budget}元\"\n        }\n    }\n    \n    config = configurations.get(usage, configurations[\"办公\"])\n    \n    return {\n        \"status\": \"success\",\n        \"usage\": usage,\n        \"budget\": budget,\n        \"configuration\": config,\n        \"message\": \"配置单生成成功\"\n    }\n",
  "parameters": {
    "budget": "number",
    "usage": "string"
  },
  "created_at": "2026-03-19T14:22:37.064079",
  "success_count": 0,
  "error_count": 0
}